cortex/__init__.py
cortex/api.py
trycortex_py-1.0.1.dist-info/METADATA
trycortex_py-1.0.1.dist-info/WHEEL
trycortex_py-1.0.1.dist-info/top_level.txt
trycortex_py-1.0.1.dist-info/RECORD
